django_ogp/__init__.py
django_ogp/admin.py
django_ogp/apps.py
django_ogp/enums.py
django_ogp/views.py
django_ogp/locale/ja/LC_MESSAGES/django.mo
django_ogp/locale/ja/LC_MESSAGES/django.po
django_ogp/migrations/0001_initial.py
django_ogp/migrations/__init__.py
django_ogp/models/__init__.py
django_ogp/models/masters.py
django_ogp/models/properties.py
django_ogp/templates/django_ogp/ogp_meta.html
django_ogp/templatetags/__init__.py
django_ogp/templatetags/django_ogp.py
django_ogp_view-1.1.0.dist-info/METADATA
django_ogp_view-1.1.0.dist-info/WHEEL
django_ogp_view-1.1.0.dist-info/licenses/LICENSE
django_ogp_view-1.1.0.dist-info/RECORD
