Metadata-Version: 2.1
Name: django-ogp-view
Version: 1.1.0
Summary: Open Graph Protocol for Django
Project-URL: Homepage, https://github.com/taogya/DjangoOgpView
Project-URL: Bug Tracker, https://github.com/taogya/DjangoOgpView/issues
Author-email: Taogya <132679709+taogya@users.noreply.github.com>
License: BSD 3-Clause License
License-File: LICENSE
Classifier: License :: OSI Approved :: BSD License
Classifier: Operating System :: POSIX :: Linux
Classifier: Programming Language :: Python :: 3
Requires-Python: >=3.9
